wrapslurm/__init__.py
wrapslurm/cancel_job.py
wrapslurm/interactive_config.py
wrapslurm/job_runner.py
wrapslurm/main_help.py
wrapslurm/node_info.py
wrapslurm/queue_info.py
wrapslurm/track_job.py
wrapslurm-0.1.9.dist-info/licenses/LICENSE
wrapslurm-0.1.9.dist-info/METADATA
wrapslurm-0.1.9.dist-info/WHEEL
wrapslurm-0.1.9.dist-info/entry_points.txt
wrapslurm-0.1.9.dist-info/top_level.txt
wrapslurm-0.1.9.dist-info/RECORD
