Metadata-Version: 2.4
Name: WrapSlurm
Version: 0.1.9
Summary: A utility for managing SLURM jobs and nodes with enhanced display features.
Home-page: https://github.com/voidful/WrapSlurm
Author: Voidful
Author-email: voidful@eric-lam.com
License: MIT
Classifier: Programming Language :: Python :: 3
Classifier: License :: OSI Approved :: MIT License
Classifier: Operating System :: OS Independent
Requires-Python: >=3.6
License-File: LICENSE
Requires-Dist: terminaltables
Requires-Dist: termcolor
Requires-Dist: questionary
Dynamic: author
Dynamic: author-email
Dynamic: classifier
Dynamic: description
Dynamic: description-content-type
Dynamic: home-page
Dynamic: license
Dynamic: license-file
Dynamic: requires-dist
Dynamic: requires-python
Dynamic: summary
